burla/__init__.py
burla/_auth.py
burla/_background_stuff.py
burla/_helpers.py
burla/_install.py
burla/_remote_parallel_map.py
burla-1.3.31.dist-info/METADATA
burla-1.3.31.dist-info/WHEEL
burla-1.3.31.dist-info/entry_points.txt
burla-1.3.31.dist-info/RECORD
