Metadata-Version: 2.4
Name: burla
Version: 1.3.31
Summary: Easy to use cluster-compute software.
Requires-Python: >=3.10
Requires-Dist: aiohttp>=3.13.2
Requires-Dist: cloudpickle>=3.1.1
Requires-Dist: fire>=0.7.1
Requires-Dist: google-cloud-firestore>=2.21.0
Requires-Dist: packaging>=25.0
Requires-Dist: platformdirs>=4.5.0
Requires-Dist: requests==2.32.4
Requires-Dist: six>=1.17.0
Requires-Dist: tblib>=3.2.0
Requires-Dist: yaspin>=3.3.0
